yangsuite/YANGSuite-10-1612190158.pdf
yangsuite/__init__.py
yangsuite/_version.py
yangsuite/application.py
yangsuite/apps.py
yangsuite/asgi.py
yangsuite/celery_init.py
yangsuite/common.py
yangsuite/context_processors.py
yangsuite/forms.py
yangsuite/logs.py
yangsuite/manage.py
yangsuite/middleware.py
yangsuite/paths.py
yangsuite/plugins.py
yangsuite/signals.py
yangsuite/socketio_config.py
yangsuite/sphinx_conf.py
yangsuite/urls.py
yangsuite/views.py
yangsuite/wsgi.py
yangsuite/data/README.md
yangsuite/data/gtm.txt
yangsuite/settings/__init__.py
yangsuite/settings/base.py
yangsuite/settings/production.py
yangsuite/static/yangsuite/css/cui-standard-1.2.2.min.css
yangsuite/static/yangsuite/css/cui-standard-1.3.3.min.css
yangsuite/static/yangsuite/css/cui-standard.min.css
yangsuite/static/yangsuite/css/yangsuite-cui.css
yangsuite/static/yangsuite/css/yangsuite_logs.css
yangsuite/static/yangsuite/css/yangsuite_plugins.css
yangsuite/static/yangsuite/css/excite-bike/jquery-ui.css
yangsuite/static/yangsuite/css/excite-bike/jquery-ui.min.css
yangsuite/static/yangsuite/css/excite-bike/theme.css
yangsuite/static/yangsuite/css/excite-bike/images/ui-bg_diagonals-small_25_c5ddfc_40x40.png
yangsuite/static/yangsuite/css/excite-bike/images/ui-bg_diagonals-thick_20_e69700_40x40.png
yangsuite/static/yangsuite/css/excite-bike/images/ui-bg_diagonals-thick_22_1484e6_40x40.png
yangsuite/static/yangsuite/css/excite-bike/images/ui-bg_diagonals-thick_26_2293f7_40x40.png
yangsuite/static/yangsuite/css/excite-bike/images/ui-bg_flat_0_e69700_40x100.png
yangsuite/static/yangsuite/css/excite-bike/images/ui-bg_flat_0_e6b900_40x100.png
yangsuite/static/yangsuite/css/excite-bike/images/ui-bg_highlight-soft_100_f9f9f9_1x100.png
yangsuite/static/yangsuite/css/excite-bike/images/ui-bg_inset-hard_100_eeeeee_1x100.png
yangsuite/static/yangsuite/css/excite-bike/images/ui-icons_0a82eb_256x240.png
yangsuite/static/yangsuite/css/excite-bike/images/ui-icons_0b54d5_256x240.png
yangsuite-3.0.8.dist-info/licenses/LICENSE.txt
yangsuite-3.0.8.dist-info/METADATA
yangsuite-3.0.8.dist-info/WHEEL
yangsuite-3.0.8.dist-info/entry_points.txt
yangsuite-3.0.8.dist-info/top_level.txt
yangsuite-3.0.8.dist-info/RECORD
